<annotation>
	<folder>fillter_title</folder>
	<filename>gesh_452454_308075_20.jpg</filename>
	<path>C:\Users\Yulong WANG\OneDrive - The University of Tokyo\satellite image\fillter_title\gesh_452454_308075_20.jpg</path>
	<source>
		<database>Unknown</database>
	</source>
	<size>
		<width>256</width>
		<height>256</height>
		<depth>3</depth>
	</size>
	<segmented>0</segmented>
	<object>
		<name>square_solid</name>
		<pose>Unspecified</pose>
		<truncated>1</truncated>
		<difficult>0</difficult>
		<bndbox>
			<xmin>195</xmin>
			<ymin>1</ymin>
			<xmax>244</xmax>
			<ymax>17</ymax>
		</bndbox>
	</object>
	<object>
		<name>square_solid</name>
		<pose>Unspecified</pose>
		<truncated>0</truncated>
		<difficult>0</difficult>
		<bndbox>
			<xmin>204</xmin>
			<ymin>9</ymin>
			<xmax>252</xmax>
			<ymax>51</ymax>
		</bndbox>
	</object>
</annotation>
